lndmanage/__init__.py
lndmanage/lndmanage.py
lndmanage/settings.py
lndmanage/grpc_compiled/__init__.py
lndmanage/grpc_compiled/lightning_pb2.py
lndmanage/grpc_compiled/lightning_pb2_grpc.py
lndmanage/grpc_compiled/router_pb2.py
lndmanage/grpc_compiled/router_pb2_grpc.py
lndmanage/grpc_compiled/signer_pb2.py
lndmanage/grpc_compiled/signer_pb2_grpc.py
lndmanage/grpc_compiled/walletkit_pb2.py
lndmanage/grpc_compiled/walletkit_pb2_grpc.py
lndmanage/lib/__init__.py
lndmanage/lib/configure.py
lndmanage/lib/data_types.py
lndmanage/lib/exceptions.py
lndmanage/lib/fee_setting.py
lndmanage/lib/forwardings.py
lndmanage/lib/info.py
lndmanage/lib/liquidityhints.py
lndmanage/lib/listings.py
lndmanage/lib/ln_utilities.py
lndmanage/lib/lncli.py
lndmanage/lib/network.py
lndmanage/lib/network_info.py
lndmanage/lib/node.py
lndmanage/lib/openchannels.py
lndmanage/lib/pathfinding.py
lndmanage/lib/rating.py
lndmanage/lib/recommend_nodes.py
lndmanage/lib/report.py
lndmanage/lib/routing.py
lndmanage/lib/user.py
lndmanage/lib/utilities.py
lndmanage/templates/config_sample.ini
test/__init__.py
test/test_fee_setting.py
test/test_graph_definitions.py
test/test_liquidityhints.py
test/test_ln_utilities.py
test/test_lndmanage.py
test/test_openchannels.py
test/test_pathfinding.py
test/test_rating.py
test/testing_common.py
test/graph_definitions/__init__.py
test/graph_definitions/empty_graph.py
test/graph_definitions/routing_graph.py
test/graph_definitions/star_ring_3_liquid.py
test/graph_definitions/star_ring_4_illiquid.py
test/graph_definitions/star_ring_4_unbalanced.py
lndmanage-0.16.0.dist-info/LICENSE
lndmanage-0.16.0.dist-info/METADATA
lndmanage-0.16.0.dist-info/WHEEL
lndmanage-0.16.0.dist-info/entry_points.txt
lndmanage-0.16.0.dist-info/top_level.txt
lndmanage-0.16.0.dist-info/RECORD
