Metadata-Version: 2.1
Name: lndmanage
Version: 0.16.0
Summary: Channel management tool for lightning network daemon (LND) 
Home-page: https://github.com/bitromortac/lndmanage
Author: bitromortac
Author-email: bitromortac@protonmail.com
Classifier: Programming Language :: Python :: 3
Classifier: License :: OSI Approved :: MIT License
Classifier: Operating System :: OS Independent
Requires-Python: >=3.9.0
License-File: LICENSE
Requires-Dist: googleapis-common-protos ==1.62.0
Requires-Dist: grpcio ==1.60.0
Requires-Dist: networkx ==3.0
Requires-Dist: numpy ==1.24.2
Requires-Dist: Pygments ==2.17.2
Provides-Extra: test
Requires-Dist: lnregtest >=0.2.2 ; extra == 'test'
